cci_cli/VERSION
cci_cli/__init__.py
cci_cli/__main__.py
cci_cli/circle/api.py
cci_cli/circle/exceptions.py
cci_cli/circle/workflow.py
cci_cli/cli.py
cci_cli/commands/artifacts.py
cci_cli/commands/config.py
cci_cli/commands/jobs.py
cci_cli/commands/pipelines.py
cci_cli/commands/workflows.py
cci_cli/common/utils.py
cci_cli-0.1.3.dist-info/entry_points.txt
cci_cli-0.1.3.dist-info/WHEEL
cci_cli-0.1.3.dist-info/METADATA
cci_cli-0.1.3.dist-info/RECORD
