Metadata-Version: 2.1
Name: cci-cli
Version: 0.1.3
Summary: This is a small CircleCI CLI that allows you to interact with the CircleCI API v2
Author: Lightspeed Hospitality
Author-email: pt.hospitality.dev@lightspeedhq.com
Requires-Python: >=3.7,<4.0
Classifier: Programming Language :: Python :: 3
Classifier: Programming Language :: Python :: 3.7
Classifier: Programming Language :: Python :: 3.8
Classifier: Programming Language :: Python :: 3.9
Requires-Dist: confuse (>=1.3,<2.0)
Requires-Dist: python-dateutil (>=2.8,<3.0)
Requires-Dist: requests (>=2.24,<3.0)
Requires-Dist: tabulate (>=0.8,<0.9)
Requires-Dist: timeago (>=1.0,<2.0)
Requires-Dist: typer (>=0.3,<0.4)
